superstate/__init__.py
superstate/context.py
superstate/exception.py
superstate/machine.py
superstate/py.typed
superstate/state.py
superstate/transition.py
superstate/types.py
superstate/utils.py
superstate/config/__init__.py
superstate/config/system.py
superstate/model/__init__.py
superstate/model/action.py
superstate/model/base.py
superstate/model/communication.py
superstate/model/data.py
superstate/model/system.py
superstate/provider/__init__.py
superstate/provider/base.py
superstate/provider/context.py
superstate/provider/default.py
superstate-1.6.2a3.dist-info/licenses/LICENSE
superstate-1.6.2a3.dist-info/METADATA
superstate-1.6.2a3.dist-info/WHEEL
superstate-1.6.2a3.dist-info/top_level.txt
superstate-1.6.2a3.dist-info/RECORD
