Metadata-Version: 2.4
Name: superstate
Version: 1.6.2a3
Summary: Robust statechart for configurable automation rules.
Author-email: "Jesse P. Johnson" <jpj6652@gmail.com>
Maintainer-email: "Jesse P. Johnson" <jpj6652@gmail.com>
License: The MIT License
Project-URL: repository, https://github.com/kuwv/python-superstate
Keywords: statechart,state machine,scxml,Harel
Classifier: Development Status :: 3 - Alpha
Classifier: Intended Audience :: Developers
Classifier: License :: OSI Approved :: MIT License
Classifier: Programming Language :: Python
Classifier: Programming Language :: Python :: 3
Classifier: Programming Language :: Python :: 3.6
Classifier: Programming Language :: Python :: 3.7
Classifier: Programming Language :: Python :: 3.8
Classifier: Programming Language :: Python :: 3.9
Classifier: Programming Language :: Python :: 3.10
Classifier: Programming Language :: Python :: 3.11
Classifier: Programming Language :: Python :: 3.12
Classifier: Topic :: Software Development :: Libraries
Requires-Python: >=3.6.2
License-File: LICENSE
Requires-Dist: RestrictedPython
Requires-Dist: typing_extensions
Provides-Extra: ecmascript
Requires-Dist: js2py; extra == "ecmascript"
Provides-Extra: scxml
Requires-Dist: xmltodict; extra == "scxml"
Provides-Extra: build
Requires-Dist: build; extra == "build"
Requires-Dist: proman-versioning>=0.5.0-alpha.2; extra == "build"
Requires-Dist: twine; extra == "build"
Provides-Extra: dev
Requires-Dist: pytest>=7; extra == "dev"
Requires-Dist: pytest-benchmark>=4; extra == "dev"
Requires-Dist: pytest-cov>=2.10.0; extra == "dev"
Requires-Dist: tox>=3.25.0; extra == "dev"
Requires-Dist: mypy>=1; extra == "dev"
Requires-Dist: pylint>=3; extra == "dev"
Requires-Dist: black==22.3.0; extra == "dev"
Requires-Dist: isort>=5.10.1; extra == "dev"
Requires-Dist: flake8>=3.8.3; extra == "dev"
Requires-Dist: bandit>=1.6.2; extra == "dev"
Requires-Dist: safety>=1.9.0; extra == "dev"
Provides-Extra: docs
Requires-Dist: docstr-coverage>=1.2.0; extra == "docs"
Requires-Dist: mkdocs>=1.2; extra == "docs"
Requires-Dist: mkdocs-material>=7.2; extra == "docs"
Requires-Dist: mkdocstrings>=0.15.2; extra == "docs"
Requires-Dist: pydocstyle[toml]>=6.1.1; extra == "docs"
Dynamic: license-file
